gumly/__init__.py
gumly/checkpoint_flow.py
gumly/dimensionality_reduction.py
gumly/feature_engineering.py
gumly/files.py
gumly/geo_location.py
gumly/hyperparameter_tuning.py
gumly/imbalanced.py
gumly/metrics.py
gumly/value_validation.py
gumly-1.2.0.dist-info/LICENSE
gumly-1.2.0.dist-info/METADATA
gumly-1.2.0.dist-info/WHEEL
gumly-1.2.0.dist-info/top_level.txt
gumly-1.2.0.dist-info/RECORD
