Metadata-Version: 2.1
Name: gumly
Version: 1.2.0
Summary: Gumly
Author: GAVB Servicos de Informatica LTDA
License-File: LICENSE
Requires-Dist: lightgbm (==3.2.1)
Requires-Dist: numpy (==1.21.4)
Requires-Dist: optuna (==2.10.0)
Requires-Dist: pandas (==1.1.5)
Requires-Dist: scikit-learn (==1.0.2)
Requires-Dist: scipy (==1.7.3)
Requires-Dist: statsmodels (==0.13.1)
Requires-Dist: imbalanced-learn (==0.9.0)
Requires-Dist: imblearn (==0.0)
Requires-Dist: ibge (==0.0.5)
Requires-Dist: unidecode (==1.3.4)
Requires-Dist: dill (==0.3.5.1)
